odoo/addons/license_website_sale/LICENSE
odoo/addons/license_website_sale/README.rst
odoo/addons/license_website_sale/__init__.py
odoo/addons/license_website_sale/__manifest__.py
odoo/addons/license_website_sale/demo/demo.xml
odoo/addons/license_website_sale/i18n/de_CH.po
odoo/addons/license_website_sale/images/screen.png
odoo/addons/license_website_sale/models/__init__.py
odoo/addons/license_website_sale/models/sale_order.py
odoo/addons/license_website_sale/models/sale_order_line.py
odoo/addons/license_website_sale/readme/CONTRIBUTORS.md
odoo/addons/license_website_sale/readme/DESCRIPTION.md
odoo/addons/license_website_sale/readme/USAGE.md
odoo/addons/license_website_sale/static/description/icon.png
odoo/addons/license_website_sale/static/description/index.html
odoo/addons/license_website_sale/tests/TEST_INSTRUCTIONS.rst
odoo/addons/license_website_sale/views/sale_order.xml
odoo/addons/license_website_sale/views/website_templates.xml
odoo_addon_license_website_sale-18.0.1.0.0.dist-info/METADATA
odoo_addon_license_website_sale-18.0.1.0.0.dist-info/WHEEL
odoo_addon_license_website_sale-18.0.1.0.0.dist-info/top_level.txt
odoo_addon_license_website_sale-18.0.1.0.0.dist-info/RECORD
