Metadata-Version: 2.1
Name: odoo-addon-license_website_sale
Version: 18.0.1.0.0
Requires-Python: >=3.10
Requires-Dist: odoo-addon-license_sale==18.0.*
Requires-Dist: odoo-addon-website_sale_pricelist_fixed_discount==18.0.*
Requires-Dist: odoo==18.0.*
Summary: Purchase licenses in the Odoo shop.
Home-page: https://www.mint-system.ch/
License: AGPL-3
Author: Mint System GmbH
Classifier: Programming Language :: Python
Classifier: Framework :: Odoo
Classifier: Framework :: Odoo :: 18.0
Classifier: License :: OSI Approved :: GNU Affero General Public License v3
